Metadata-Version: 2.1
Name: nmea
Version: 0.1.4
Summary: Python framework for a NMEA 0183 TCP Server inspired by Flask developer API
Home-page: https://github.com/robonation/nmea
Author: Felix Pageau
Author-email: pageau@robonation.org
License: Apache License 2.0
Download-URL: https://github.com/robonation/nmea/archive/v0.1.4.tar.gz
Keywords: NMEA,SERVER,FRAMEWORK
Platform: UNKNOWN
Classifier: Development Status :: 3 - Alpha
Classifier: Intended Audience :: Science/Research
Classifier: License :: OSI Approved :: Apache Software License
Classifier: Operating System :: OS Independent
Classifier: Programming Language :: Python
Classifier: Programming Language :: Python :: 2
Classifier: Programming Language :: Python :: 2.7
Classifier: Programming Language :: Python :: 3
Classifier: Programming Language :: Python :: 3.4
Classifier: Programming Language :: Python :: 3.5
Classifier: Programming Language :: Python :: 3.6
Classifier: Programming Language :: Python :: 3.7
Requires-Python: >=2.7,!=3.0.*,!=3.1.*,!=3.2.*,!=3.3.*
